LICENSE
README.md
setup.cfg
setup.py
easyaug/__init__.py
easyaug.egg-info/PKG-INFO
easyaug.egg-info/SOURCES.txt
easyaug.egg-info/dependency_links.txt
easyaug.egg-info/requires.txt
easyaug.egg-info/top_level.txt
easyaug/augment/__init__.py
easyaug/augment/augmenter.py
easyaug/augment/augmenting_types.py
easyaug/augment/run_augment.py
easyaug/augment/run_view.py
easyaug/preprocess/__init__.py
easyaug/preprocess/preprocesser.py
easyaug/preprocess/resize.py
easyaug/quickview/__init__.py
easyaug/quickview/quickviewer.py
easyaug/quickview/read.py
easyaug/quickview/view.py