Metadata-Version: 2.1
Name: easyaug
Version: 1.0.1
Summary: A package to fast and easy view, prepare and augment images
Home-page: UNKNOWN
Author: Simon Myhre
Author-email: simonmyhre1@gmail.com
License: UNKNOWN
Platform: UNKNOWN
License-File: LICENSE
